ReactJsXiaoShu20170503/README.md
ReactJsXiaoShu20170503/__init__.py
ReactJsXiaoShu20170503/__main__.py
ReactJsXiaoShu20170503/file.epub
ReactJsXiaoShu20170503/index.html
ReactJsXiaoShu20170503/css/__init__.py
ReactJsXiaoShu20170503/css/annotations.css
ReactJsXiaoShu20170503/css/main.css
ReactJsXiaoShu20170503/css/normalize.css
ReactJsXiaoShu20170503/css/popup.css
ReactJsXiaoShu20170503/font/__init__.py
ReactJsXiaoShu20170503/font/fontello.eot
ReactJsXiaoShu20170503/font/fontello.svg
ReactJsXiaoShu20170503/font/fontello.ttf
ReactJsXiaoShu20170503/font/fontello.woff
ReactJsXiaoShu20170503/img/__init__.py
ReactJsXiaoShu20170503/img/annotator-glyph-sprite.png
ReactJsXiaoShu20170503/img/annotator-icon-sprite.png
ReactJsXiaoShu20170503/img/apple-touch-icon.png
ReactJsXiaoShu20170503/img/cancelfullscreen.png
ReactJsXiaoShu20170503/img/close.png
ReactJsXiaoShu20170503/img/fullscreen.png
ReactJsXiaoShu20170503/img/loader.gif
ReactJsXiaoShu20170503/img/menu-icon.png
ReactJsXiaoShu20170503/img/save.png
ReactJsXiaoShu20170503/img/saved.png
ReactJsXiaoShu20170503/img/settings-s.png
ReactJsXiaoShu20170503/img/settings.png
ReactJsXiaoShu20170503/img/star.png
ReactJsXiaoShu20170503/js/__init__.py
ReactJsXiaoShu20170503/js/epub.js
ReactJsXiaoShu20170503/js/epub.min.js
ReactJsXiaoShu20170503/js/epub.min.map
ReactJsXiaoShu20170503/js/hooks.min.js
ReactJsXiaoShu20170503/js/hooks.min.map
ReactJsXiaoShu20170503/js/reader.js
ReactJsXiaoShu20170503/js/reader.js.map
ReactJsXiaoShu20170503/js/reader.min.js
ReactJsXiaoShu20170503/js/reader.min.map
ReactJsXiaoShu20170503/js/hooks/__init__.py
ReactJsXiaoShu20170503/js/hooks/extensions/__init__.py
ReactJsXiaoShu20170503/js/hooks/extensions/highlight.js
ReactJsXiaoShu20170503/js/libs/__init__.py
ReactJsXiaoShu20170503/js/libs/jquery.min.js
ReactJsXiaoShu20170503/js/libs/localforage.min.js
ReactJsXiaoShu20170503/js/libs/screenfull.js
ReactJsXiaoShu20170503/js/libs/screenfull.min.js
ReactJsXiaoShu20170503/js/libs/zip.min.js
react_js_xiao_shu_20170503-2024.3.2.0.dist-info/METADATA
react_js_xiao_shu_20170503-2024.3.2.0.dist-info/WHEEL
react_js_xiao_shu_20170503-2024.3.2.0.dist-info/entry_points.txt
react_js_xiao_shu_20170503-2024.3.2.0.dist-info/top_level.txt
react_js_xiao_shu_20170503-2024.3.2.0.dist-info/RECORD
